grpc4bmi/__init__.py
grpc4bmi/bmi_client_apptainer.py
grpc4bmi/bmi_client_docker.py
grpc4bmi/bmi_client_singularity.py
grpc4bmi/bmi_client_subproc.py
grpc4bmi/bmi_grpc_client.py
grpc4bmi/bmi_grpc_legacy_server.py
grpc4bmi/bmi_grpc_server.py
grpc4bmi/bmi_julia_model.py
grpc4bmi/bmi_memoized.py
grpc4bmi/bmi_optionaldest.py
grpc4bmi/bmi_pb2.py
grpc4bmi/bmi_pb2_grpc.py
grpc4bmi/bmi_r_model.py
grpc4bmi/constants.py
grpc4bmi/exceptions.py
grpc4bmi/py.typed
grpc4bmi/reserve.py
grpc4bmi/run_server.py
grpc4bmi-0.5.0.dist-info/LICENSE
grpc4bmi-0.5.0.dist-info/METADATA
grpc4bmi-0.5.0.dist-info/WHEEL
grpc4bmi-0.5.0.dist-info/entry_points.txt
grpc4bmi-0.5.0.dist-info/top_level.txt
grpc4bmi-0.5.0.dist-info/RECORD
