Metadata-Version: 2.1
Name: grpc4bmi
Version: 0.5.0
Summary: Run your BMI implementation in a separate process and expose it as BMI-python with GRPC
License: Apache License 2.0
Project-URL: Homepage, https://github.com/eWaterCycle/grpc4bmi
Project-URL: Bug Tracker, https://github.com/eWaterCycle/grpc4bmi/issues
Project-URL: Documentation, https://grpc4bmi.readthedocs.io/
Project-URL: Source code, https://github.com/eWaterCycle/grpc4bmi
Classifier: Development Status :: 3 - Alpha
Classifier: Intended Audience :: Science/Research
Classifier: Programming Language :: Python
Classifier: Operating System :: OS Independent
Classifier: Programming Language :: Python :: 3.7
Classifier: Programming Language :: Python :: 3.8
Classifier: Programming Language :: Python :: 3.9
Classifier: Programming Language :: Python :: 3.10
Classifier: Programming Language :: Python :: 3.11
Classifier: Topic :: Utilities
Classifier: Topic :: Scientific/Engineering
Classifier: License :: OSI Approved :: Apache Software License
Requires-Python: >=3.7
License-File: LICENSE
Requires-Dist: grpcio
Requires-Dist: grpcio-reflection
Requires-Dist: grpcio-status
Requires-Dist: googleapis-common-protos >=1.5.5
Requires-Dist: protobuf <5,>=4
Requires-Dist: numpy
Requires-Dist: docker
Requires-Dist: bmipy
Requires-Dist: packaging
Requires-Dist: typeguard
Provides-Extra: r
Requires-Dist: rpy2 ; extra == 'r'
Provides-Extra: dev
Requires-Dist: build ; extra == 'dev'
Requires-Dist: pytest ; extra == 'dev'
Requires-Dist: pytest-cov ; extra == 'dev'
Requires-Dist: coverage[toml] ; extra == 'dev'
Requires-Dist: grpcio-tools ; extra == 'dev'
Requires-Dist: nbconvert ; extra == 'dev'
Requires-Dist: ipykernel ; extra == 'dev'
Requires-Dist: nbformat ; extra == 'dev'
Provides-Extra: docs
Requires-Dist: sphinx ; extra == 'docs'
Requires-Dist: sphinxcontrib-apidoc ; extra == 'docs'
Requires-Dist: sphinxcontrib-napoleon ; extra == 'docs'
Requires-Dist: sphinxcontrib-jquery ; extra == 'docs'
Requires-Dist: sphinx-argparse ; extra == 'docs'
Requires-Dist: sphinx-rtd-theme >=1.0.0 ; extra == 'docs'
Requires-Dist: numpydoc ; extra == 'docs'
Requires-Dist: sphinx-copybutton ; extra == 'docs'
Provides-Extra: julia
Requires-Dist: juliacall ; extra == 'julia'
